{"data":{"user":{"name":"Joan Marcè i Igual","bio":"PhD Candidate at TU/e","avatarUrl":"https://avatars.githubusercontent.com/u/6493651?u=09efe3113d1a4db807b4b403e6dccab6759dcf25&v=4","location":"The Netherlands","pinnedItems":{"totalCount":5,"edges":[{"node":{"name":"dotfiles","description":"Personal dotfiles","forkCount":0,"stargazers":{"totalCount":1},"url":"https://github.com/jmigual/dotfiles","id":"MDEwOlJlcG9zaXRvcnk3MTE2MjQ1Mw==","diskUsage":473,"primaryLanguage":{"name":"Shell","color":"#89e051"}}},{"node":{"name":"modern-cmake-cpp-starter","description":"Starter project for modern CMake and C++20","forkCount":1,"stargazers":{"totalCount":1},"url":"https://github.com/jmigual/modern-cmake-cpp-starter","id":"R_kgDOMH8b0Q","diskUsage":29,"primaryLanguage":{"name":"CMake","color":"#DA3434"}}},{"node":{"name":"TRAINer","description":"A project about creating a beautiful map of trains for a selected area.","forkCount":0,"stargazers":{"totalCount":0},"url":"https://github.com/jmigual/TRAINer","id":"R_kgDOLLOO5w","diskUsage":667,"primaryLanguage":{"name":"C#","color":"#178600"}}},{"node":{"name":"slurmer","description":"A package to schedule different tasks in parallel with cluster support.","forkCount":0,"stargazers":{"totalCount":0},"url":"https://github.com/jmigual/slurmer","id":"R_kgDOGWJtlQ","diskUsage":2984,"primaryLanguage":{"name":"Python","color":"#3572A5"}}},{"node":{"name":"typst-efilrst","description":"A simple referenceable list library for typst.","forkCount":0,"stargazers":{"totalCount":0},"url":"https://github.com/jmigual/typst-efilrst","id":"R_kgDOMnciew","diskUsage":317,"primaryLanguage":{"name":"Typst","color":"#239dad"}}}]}}}}